{
  "title": "Paizo Token Art",
  "description": "A module to add Paizo related art",
  "authors": [
    {
      "name": "Zullock",
      "discord": "Zullock#2883",
      "flags": {}
    }
  ],
  "version": "3.5.0",
  "compatibility": {
    "minimum": "10.291",
    "verified": "12"
  },
  "url": "https://github.com/Zullock/pf2e-token-art",
  "manifest": "https://raw.githubusercontent.com/Zullock/pf2e-token-art/main/module.json",
  "download": "https://github.com/Zullock/pf2e-token-art/archive/refs/tags/v3.5.0.zip",
  "changelog": "https://github.com/Zullock/pf2e-token-art/blob/main/CHANGELOG.md",
  "flags": {
   "galleryDatasheets": {
        "pf1e-adventure-path-datasheet": {
            "label": "PF1e Adventure Paths",
            "sheet": "modules/pf2e-token-art/data/PF1e/adventure-path-datasheet.json"
        },
        "pf1e-module-datasheet": {
            "label": "PF1e Modules",
            "sheet": "modules/pf2e-token-art/data/PF1e/module-datasheet.json"
        },
        "pf1e-rulebook-datasheet": {
            "label": "PF1e Rulebooks",
            "sheet": "modules/pf2e-token-art/data/PF1e/rulebook-datasheet.json"
        },
        "pf2e-adventure-path-frozen-flame-datasheet": {
          "label": "PF2e AP Quest for the Frozen Flame",
          "sheet": "modules/pf2e-token-art/data/PF2e/adventure-path/adventure-path-frozen-flame-datasheet.json"
        },
        "pf2e-rulebook-book-of-the-dead-datasheet": {
          "label": "PF2e Rulebook Book of the Dead",
          "sheet": "modules/pf2e-token-art/data/PF2e/rulebook/rulebook-book-of-the-dead-datasheet.json"
        }
    },
    "compendiumArtMappings": {
      "pf2e": {
        "mapping": "modules/pf2e-token-art/data/map-art-tokens.json"
      }
    }
  },
  "relationships": {
    "systems": [
      {
        "id": "pf2e",
        "type": "system",
        "manifest": "https://raw.githubusercontent.com/foundryvtt/pf2e/master/system.json",
        "compatibility": {
          "minimum": "4.8.1"
        }
      }
    ]
  },
  "id": "pf2e-token-art"
}
